pywebviewcv/__init__.py
pywebviewcv/web_canvas.py
pywebviewcv-2.dist-info/LICENSE
pywebviewcv-2.dist-info/METADATA
pywebviewcv-2.dist-info/WHEEL
pywebviewcv-2.dist-info/top_level.txt
pywebviewcv-2.dist-info/RECORD
